GeoModelingZ/__init__.py
GeoModelingZ/core.py
geomodelingz-0.0.6.dist-info/licenses/LICENSE
geomodelingz-0.0.6.dist-info/METADATA
geomodelingz-0.0.6.dist-info/WHEEL
geomodelingz-0.0.6.dist-info/top_level.txt
geomodelingz-0.0.6.dist-info/RECORD
