Metadata-Version: 2.4
Name: GeoModelingZ
Version: 0.0.6
Summary: 地理建模与可视化工具库
Home-page: https://github.com/Zhoums396/GeoModelingZ
Author: Zhoums
Author-email: 18652950852@163.com
Classifier: Programming Language :: Python :: 3
Classifier: License :: OSI Approved :: MIT License
Classifier: Operating System :: OS Independent
Classifier: Development Status :: 4 - Beta
Classifier: Intended Audience :: Developers
Classifier: Intended Audience :: Science/Research
Classifier: Topic :: Scientific/Engineering :: GIS
Classifier: Topic :: Scientific/Engineering :: Visualization
Requires-Python: >=3.6
License-File: LICENSE
Requires-Dist: numpy
Requires-Dist: matplotlib
Requires-Dist: ipython
Requires-Dist: folium
Provides-Extra: jupyter
Requires-Dist: ipywidgets>=7.0.0; extra == "jupyter"
Requires-Dist: jupyterlab_widgets; extra == "jupyter"
Dynamic: author
Dynamic: author-email
Dynamic: classifier
Dynamic: description
Dynamic: description-content-type
Dynamic: home-page
Dynamic: license-file
Dynamic: provides-extra
Dynamic: requires-dist
Dynamic: requires-python
Dynamic: summary
